LICENSE
mongojuuid/__init__.py
mongojuuid/__main__.py
mongojuuid/main.py
mongojuuid-0.1.2.dist-info/entry_points.txt
mongojuuid-0.1.2.dist-info/LICENSE
mongojuuid-0.1.2.dist-info/WHEEL
mongojuuid-0.1.2.dist-info/METADATA
mongojuuid-0.1.2.dist-info/RECORD
