Metadata-Version: 2.1
Name: mongojuuid
Version: 0.1.2
Summary: CLI to convert BinData Subtype 3 to JUUID and vice-versa
Home-page: https://github.com/luxmeter/mongojuuid
License: MIT
Keywords: mongo,uuid,java
Author: Mustafa Caylak
Author-email: mustafa.caylak@web.de
Requires-Python: >=3.8,<4.0
Classifier: License :: OSI Approved :: MIT License
Classifier: Programming Language :: Python :: 3
Classifier: Programming Language :: Python :: 3.8
Classifier: Programming Language :: Python :: 3.9
Classifier: Topic :: Database
Classifier: Topic :: Software Development
Classifier: Topic :: Software Development :: Libraries :: Python Modules
Requires-Dist: typer (>=0.3.2,<0.4.0)
Project-URL: Repository, https://github.com/luxmeter/mongojuuid
